argparseinator/__init__.py
argparseinator/__main__.py
argparseinator/exceptions.py
argparseinator/sphinx_extensions.py
argparseinator/utils.py
argparseinator/skeleton/standalone/project.py
argparseinator/skeleton/standalone/project/__init__.py
argparseinator/skeleton/standalone/project/commands.py
argparseinator/skeleton/submodules/project.py
argparseinator/skeleton/submodules/project/__init__.py
argparseinator/skeleton/submodules/project/commands.py
argparseinator/skeleton/submodules/submodule/__init__.py
argparseinator/skeleton/submodules/submodule/commands.py
argparseinator/skeleton/subprojects/project.py
argparseinator/skeleton/subprojects/project/__init__.py
argparseinator/skeleton/subprojects/project/utils.py
argparseinator/skeleton/subprojects/submodule/__init__.py
argparseinator/skeleton/subprojects/submodule/commands.py
ArgParseInator-1.3.0.dist-info/LICENSE.md
ArgParseInator-1.3.0.dist-info/METADATA
ArgParseInator-1.3.0.dist-info/WHEEL
ArgParseInator-1.3.0.dist-info/top_level.txt
ArgParseInator-1.3.0.dist-info/RECORD
