Metadata-Version: 2.1
Name: ArgParseInator
Version: 1.3.0
Summary: Decorators and wrapper for easily define script's arguments within functions and classes. just defining function's args.
Home-page: https://github.com/ellethee/argparseinator
Author: ellethee
Author-email: luca800@gmail.com
License: MIT
Keywords: simple arguments argumentparser options args command line argparse optparse optionparser script
Platform: UNKNOWN
Classifier: Development Status :: 5 - Production/Stable
Classifier: Intended Audience :: Developers
Classifier: Topic :: Software Development :: Testing
Classifier: License :: OSI Approved :: MIT License
Classifier: Programming Language :: Python :: 3
Requires-Python: >=3.5
